rdfc/__init__.py
rdfc/__main__.py
rdfc-0.2.6.dist-info/METADATA
rdfc-0.2.6.dist-info/WHEEL
rdfc-0.2.6.dist-info/entry_points.txt
rdfc-0.2.6.dist-info/top_level.txt
rdfc-0.2.6.dist-info/RECORD
