Metadata-Version: 2.1
Name: rdfc
Version: 0.2.6
Summary: Convert RDF files to any serialization format via rdflib
Author-email: svenrdz <srodriguez@ipsl.fr>
License: BSD-3-Clause
Classifier: License :: OSI Approved :: BSD License
Requires-Python: >=3.8
Requires-Dist: rdflib >=6.3.2
Requires-Dist: typer[all] >=0.9.0
